src/VersionUtil.py
src/__init__.py
REMLA23_team09_lib-0.0.1.dist-info/METADATA
REMLA23_team09_lib-0.0.1.dist-info/WHEEL
REMLA23_team09_lib-0.0.1.dist-info/top_level.txt
REMLA23_team09_lib-0.0.1.dist-info/RECORD
